plover_midi/__init__.py
plover_midi/machine.py
plover_midi/gui_qt/__init__.py
plover_midi/gui_qt/midi_option.py
plover_midi/gui_qt/midi_widget_ui.py
plover_midi-1.0.5.dist-info/METADATA
plover_midi-1.0.5.dist-info/WHEEL
plover_midi-1.0.5.dist-info/entry_points.txt
plover_midi-1.0.5.dist-info/top_level.txt
plover_midi-1.0.5.dist-info/zip-safe
plover_midi-1.0.5.dist-info/RECORD
